geeadd/__init__.py
geeadd/acl_changer.py
geeadd/app2script.py
geeadd/batch_copy.py
geeadd/batch_delete.py
geeadd/batch_mover.py
geeadd/ee_del_meta.py
geeadd/ee_projects.py
geeadd/ee_report.py
geeadd/geeadd.py
geeadd-1.2.1.data/data/LICENSE
geeadd-1.2.1.dist-info/LICENSE
geeadd-1.2.1.dist-info/METADATA
geeadd-1.2.1.dist-info/WHEEL
geeadd-1.2.1.dist-info/entry_points.txt
geeadd-1.2.1.dist-info/top_level.txt
geeadd-1.2.1.dist-info/RECORD
