Metadata-Version: 2.2
Name: geeadd
Version: 1.2.1
Summary: Google Earth Engine Batch Assets Manager with Addons
Home-page: https://github.com/samapriya/gee_asset_manager_addon
Author: Samapriya Roy
Author-email: samapriya.roy@gmail.com
License: Apache 2.0
Classifier: Development Status :: 5 - Production/Stable
Classifier: Intended Audience :: Developers
Classifier: Intended Audience :: Science/Research
Classifier: Natural Language :: English
Classifier: License :: OSI Approved :: Apache Software License
Classifier: Programming Language :: Python :: 3
Classifier: Programming Language :: Python :: 3.7
Classifier: Programming Language :: Python :: 3.8
Classifier: Operating System :: OS Independent
Classifier: Topic :: Scientific/Engineering :: GIS
Requires-Python: >=3.7
License-File: LICENSE
Requires-Dist: colorama>=0.4.6
Requires-Dist: earthengine-api>=1.1.2
Requires-Dist: jsbeautifier>=1.15.1
Requires-Dist: logzero>=1.7.0
Requires-Dist: packaging>=24.2
Requires-Dist: requests>=2.32.3
Requires-Dist: setuptools>=65.5.0
Requires-Dist: tqdm>=4.66.5
Requires-Dist: beautifulsoup4>=4.9.0
Dynamic: author
Dynamic: author-email
Dynamic: classifier
Dynamic: description
Dynamic: description-content-type
Dynamic: home-page
Dynamic: license
Dynamic: requires-dist
Dynamic: requires-python
Dynamic: summary
